{   
    "name" : "Juggernaut",
    "repItem" : {
        "item_type" : "AIR"
    },
    "items" : [
        {
            "item_type" : "STICK",
            "title" : "&bBeat Stick",
            "lore" : [
                "&bStand Aside",
                "&aBe gone!"
            ],
            "enchants" : [
                {
                    "name" : "KNOCKBACK",
                    "level" : 3
                },
                {
                    "name" : "DAMAGE_ALL",
                    "level" : 3
                }
            ]
        }
    ],
    "status_effects" : [
        {
            "name" : "ABSORPTION",
            "level" : 3,
            "ambient" : false
        }
    ],
    "armour" : [
        {
            "item_type" : "LEATHER_HELMET",
            "title" : "&bUnbreaking",
            "lore" : [
                "&bImpervious!"
            ],
            "color" : "#666666"
        },
        {
            "item_type" : "LEATHER_CHESTPLATE",
            "title" : "&bUnbreaking",
            "lore" : [
                "&bImpervious!"
            ],
            "color" : "#666666"
        },
        {
            "item_type" : "LEATHER_LEGGINGS",
            "title" : "&bUnbreaking",
            "lore" : [
                "&bImpervious!"
            ],
            "color" : "#666666"
        },
        {
            "item_type" : "LEATHER_BOOTS",
            "title" : "&bUnbreaking",
            "lore" : [
                "&bImpervious!"
            ],
            "enchants" : [
                {
                    "name" : "THORNS",
                    "level" : 6
                }
            ],
            "color" : "#666666"
        }
    ]
}